core_utils_file/__init__.py
core_utils_file/data_utils.py
core_utils_file/env_utils.py
core_utils_file/file_utils.py
core_utils_file/py.typed
core_utils_file/validators.py
turintech_file_utils-1.0.0a3.dist-info/METADATA
turintech_file_utils-1.0.0a3.dist-info/WHEEL
turintech_file_utils-1.0.0a3.dist-info/licenses/LICENSE
turintech_file_utils-1.0.0a3.dist-info/RECORD
