Metadata-Version: 2.4
Name: turintech_file_utils
Version: 1.0.0a3
Summary: File, data and environment utilities
License-Expression: LicenseRef-Turing-Intelligence-Technology-EULA
License-File: LICENSE
Classifier: Development Status :: 5 - Production/Stable
Classifier: License :: Other/Proprietary License
Requires-Python: <3.14,>=3.11
Requires-Dist: packaging<25.0,>=23.0
Requires-Dist: pydantic<3.0.0,>=2
Requires-Dist: python-dotenv<2.0.0,>=0.21.0
Requires-Dist: turintech-data-types<3.0.0,>=2.0.0a0
Requires-Dist: turintech-ioc<3.0.0,>=1.1.0
